[
  {
    "adapter": "ngspice",
    "artifact_id": "D11-11-ART",
    "artifact_type": "tool_log",
    "claim_binding": "software_only_artifact_evidence",
    "created_by_command": "artifactgate synthetic-corruption-fixture",
    "evidence_level": "L3_SIMULATION",
    "relative_path": "raw_artifacts/result.log",
    "requires_seed": true,
    "sha256": "c08d83e3feaef8ca1b927bdb9713dcd4778105f0dfff9982328e40de9d5f8a9a",
    "size_bytes": 30,
    "tool": "ngspice",
    "tool_version": "ngspice-fixture-1.0",
    "unsupported_boundary": "none"
  }
]