[
  {
    "adapter": "ngspice",
    "artifact_id": "D06-05-ART",
    "artifact_type": "tool_log",
    "checksum_state": "stale",
    "claim_binding": "software_only_artifact_evidence",
    "created_by_command": "artifactgate synthetic-corruption-fixture",
    "evidence_level": "L3_SIMULATION",
    "relative_path": "raw_artifacts/result.log",
    "sha256": "c4902a5eabbfd3ba482a99d72f9e29b03c7b6f852a852ed52bb3122051c904ad",
    "size_bytes": 30,
    "tool": "ngspice",
    "tool_version": "ngspice-fixture-1.0",
    "unsupported_boundary": "none"
  }
]