[
  {
    "adapter": "ngspice",
    "artifact_id": "D17-25-ART",
    "artifact_type": "tool_log",
    "claim_binding": "software_only_artifact_evidence",
    "created_by_command": "artifactgate synthetic-corruption-fixture",
    "evidence_level": "L3_SIMULATION",
    "relative_path": "raw_artifacts/result.log",
    "sha256": "85f3ab3bdbefbd7be53a5afea65cb1864eaf06f152d46950aa7c7e09cb7c5b6d",
    "size_bytes": 30,
    "tool": "ngspice",
    "tool_version": "ngspice-fixture-1.0",
    "unsupported_boundary": "none"
  }
]