[
  {
    "adapter": "ngspice",
    "artifact_id": "D19-09-ART",
    "artifact_type": "tool_log",
    "claim_binding": "software_only_artifact_evidence",
    "created_by_command": "artifactgate synthetic-corruption-fixture",
    "evidence_level": "L3_SIMULATION",
    "relative_path": "raw_artifacts/result.log",
    "sha256": "326d4a3db9272ca7c52c7b5f59a5ca5deaa7d144b5271d76e804a9f90d412482",
    "size_bytes": 30,
    "tool": "ngspice",
    "tool_version": "ngspice-fixture-1.0",
    "unsupported_boundary": "none"
  }
]