[
  {
    "adapter": "ngspice",
    "artifact_id": "D06-26-ART",
    "artifact_type": "tool_log",
    "checksum_state": "stale",
    "claim_binding": "software_only_artifact_evidence",
    "created_by_command": "artifactgate synthetic-corruption-fixture",
    "evidence_level": "L3_SIMULATION",
    "relative_path": "raw_artifacts/result.log",
    "sha256": "15772a34cd55d6a901c1d6f8755d3aa8f7e6940e28011341f86f3491e7c29ad8",
    "size_bytes": 30,
    "tool": "ngspice",
    "tool_version": "ngspice-fixture-1.0",
    "unsupported_boundary": "none"
  }
]