[
  {
    "adapter": "ngspice",
    "artifact_id": "D16-04-ART",
    "artifact_type": "tool_log",
    "claim_binding": "software_only_artifact_evidence",
    "created_by_command": "artifactgate synthetic-corruption-fixture",
    "evidence_level": "L3_SIMULATION",
    "relative_path": "raw_artifacts/result.log",
    "sha256": "24395f5ef6277071e40acdb47c65cb13718715bb668f467e5588e28a43805cb3",
    "size_bytes": 30,
    "tool": "ngspice",
    "tool_version": "ngspice-fixture-1.0",
    "unsupported_boundary": "none"
  }
]