[
  {
    "adapter": "ngspice",
    "artifact_id": "D12-11-ART",
    "artifact_type": "tool_log",
    "claim_binding": "software_only_artifact_evidence",
    "created_by_command": "artifactgate synthetic-corruption-fixture",
    "evidence_level": "L3_SIMULATION",
    "relative_path": "raw_artifacts/result.log",
    "sha256": "eacd2c0e5ba4e05caa88cbce81e3539e47d397ff34bef6b2ef3d3de5faa457f6",
    "size_bytes": 30,
    "tool": "ngspice",
    "tool_version": "ngspice-fixture-1.0",
    "unsupported_boundary": "none"
  }
]